parser/__init__.py
parser/constants.py
parser/nextflow.py
parser/utils.py
sb_types/__init__.py
sb_types/port.py
sb_types/requirements.py
sb_types/sb_types.py
wrabbit/__init__.py
wrabbit/exceptions.py
wrabbit/version.py
wrabbit/parser/__init__.py
wrabbit/parser/constants.py
wrabbit/parser/nextflow.py
wrabbit/parser/utils.py
wrabbit/parser/js_templates/sample_sheet_generator.js
wrabbit/parser/js_templates/sample_sheet_switch.js
wrabbit/sb_types/__init__.py
wrabbit/sb_types/port.py
wrabbit/sb_types/requirements.py
wrabbit/sb_types/sb_types.py
wrabbit/specification/__init__.py
wrabbit/specification/binding.py
wrabbit/specification/hints.py
wrabbit/specification/listing.py
wrabbit/specification/node.py
wrabbit/specification/node_types.py
wrabbit/specification/port.py
wrabbit/specification/requirements.py
wrabbit/specification/sbg.py
wrabbit/specification/utils.py
wrabbit/wrapper/__init__.py
wrabbit/wrapper/constants.py
wrabbit/wrapper/utils.py
wrabbit/wrapper/wrapper.py
wrapper/__init__.py
wrapper/constants.py
wrapper/utils.py
wrapper/wrapper.py
wrabbit-0.3.1.dist-info/LICENSE
wrabbit-0.3.1.dist-info/METADATA
wrabbit-0.3.1.dist-info/WHEEL
wrabbit-0.3.1.dist-info/top_level.txt
wrabbit-0.3.1.dist-info/RECORD
